{
    "1": {
        "Comment": " KIF形式棋譜ファイル"
    },
    "2": {
        "Comment": " Generated by Shogidokoro"
    },
    "3": {
        "Handicap": "Hirate"
    },
    "4": {
        "PlayerPhase": "FirstPlayer",
        "PlayerName": "Kifuwarabe"
    },
    "5": {
        "PlayerPhase": "SecondPlayer",
        "PlayerName": "NEEDLED-35.8kai1915"
    },
    "7": {
        "Moves": "1",
        "ElapsedTime": {
            "Minute": 0,
            "Second": 0
        },
        "TotalElapsedTime": {
            "Hour": 0,
            "Minute": 0,
            "Second": 0
        },
        "Move": {
            "DestinationFile": 4,
            "DestinationRank": 6,
            "PieceType": "Pawn",
            "SourceFile": 4,
            "SourceRank": 7
        }
    },
    "8": {
        "Moves": "2",
        "ElapsedTime": {
            "Minute": 0,
            "Second": 13
        },
        "TotalElapsedTime": {
            "Hour": 0,
            "Minute": 0,
            "Second": 13
        },
        "Move": {
            "DestinationFile": 8,
            "DestinationRank": 4,
            "PieceType": "Pawn",
            "SourceFile": 8,
            "SourceRank": 3
        }
    },
    "9": {
        "Moves": "3",
        "ElapsedTime": {
            "Minute": 0,
            "Second": 0
        },
        "TotalElapsedTime": {
            "Hour": 0,
            "Minute": 0,
            "Second": 0
        },
        "Move": {
            "DestinationFile": 9,
            "DestinationRank": 6,
            "PieceType": "Pawn",
            "SourceFile": 9,
            "SourceRank": 7
        }
    },
    "10": {
        "Moves": "4",
        "ElapsedTime": {
            "Minute": 0,
            "Second": 10
        },
        "TotalElapsedTime": {
            "Hour": 0,
            "Minute": 0,
            "Second": 23
        },
        "Move": {
            "DestinationFile": 8,
            "DestinationRank": 5,
            "PieceType": "Pawn",
            "SourceFile": 8,
            "SourceRank": 4
        }
    },
    "11": {
        "Moves": "5",
        "ElapsedTime": {
            "Minute": 0,
            "Second": 0
        },
        "TotalElapsedTime": {
            "Hour": 0,
            "Minute": 0,
            "Second": 0
        },
        "Move": {
            "DestinationFile": 7,
            "DestinationRank": 8,
            "PieceType": "Gold",
            "SourceFile": 6,
            "SourceRank": 9
        }
    },
    "12": {
        "Moves": "6",
        "ElapsedTime": {
            "Minute": 0,
            "Second": 14
        },
        "TotalElapsedTime": {
            "Hour": 0,
            "Minute": 0,
            "Second": 37
        },
        "Move": {
            "DestinationFile": 8,
            "DestinationRank": 6,
            "PieceType": "Pawn",
            "SourceFile": 8,
            "SourceRank": 5
        }
    },
    "13": {
        "Moves": "7",
        "ElapsedTime": {
            "Minute": 0,
            "Second": 0
        },
        "TotalElapsedTime": {
            "Hour": 0,
            "Minute": 0,
            "Second": 0
        },
        "Move": {
            "DestinationFile": 6,
            "DestinationRank": 8,
            "PieceType": "King",
            "SourceFile": 5,
            "SourceRank": 9
        }
    },
    "14": {
        "Moves": "8",
        "ElapsedTime": {
            "Minute": 0,
            "Second": 7
        },
        "TotalElapsedTime": {
            "Hour": 0,
            "Minute": 0,
            "Second": 44
        },
        "Move": {
            "DestinationFile": 8,
            "DestinationRank": 7,
            "PieceType": "Pawn",
            "Promotion": true,
            "SourceFile": 8,
            "SourceRank": 6
        }
    },
    "15": {
        "Moves": "9",
        "ElapsedTime": {
            "Minute": 0,
            "Second": 0
        },
        "TotalElapsedTime": {
            "Hour": 0,
            "Minute": 0,
            "Second": 0
        },
        "Move": {
            "DestinationFile": 4,
            "DestinationRank": 5,
            "PieceType": "Pawn",
            "SourceFile": 4,
            "SourceRank": 6
        }
    },
    "16": {
        "Moves": "10",
        "ElapsedTime": {
            "Minute": 0,
            "Second": 7
        },
        "TotalElapsedTime": {
            "Hour": 0,
            "Minute": 0,
            "Second": 51
        },
        "Move": {
            "DestinationFile": 7,
            "DestinationRank": 8,
            "PieceType": "PromotionPawn",
            "SourceFile": 8,
            "SourceRank": 7
        }
    },
    "17": {
        "Moves": "11",
        "ElapsedTime": {
            "Minute": 0,
            "Second": 0
        },
        "TotalElapsedTime": {
            "Hour": 0,
            "Minute": 0,
            "Second": 0
        },
        "Move": {
            "DestinationFile": 5,
            "DestinationRank": 9,
            "PieceType": "King",
            "SourceFile": 6,
            "SourceRank": 8
        }
    },
    "18": {
        "Moves": "12",
        "ElapsedTime": {
            "Minute": 0,
            "Second": 7
        },
        "TotalElapsedTime": {
            "Hour": 0,
            "Minute": 0,
            "Second": 58
        },
        "Move": {
            "DestinationFile": 7,
            "DestinationRank": 9,
            "PieceType": "PromotionPawn",
            "SourceFile": 7,
            "SourceRank": 8
        }
    },
    "19": {
        "Moves": "13",
        "ElapsedTime": {
            "Minute": 0,
            "Second": 0
        },
        "TotalElapsedTime": {
            "Hour": 0,
            "Minute": 0,
            "Second": 0
        },
        "Move": {
            "DestinationFile": 3,
            "DestinationRank": 8,
            "PieceType": "Gold",
            "SourceFile": 4,
            "SourceRank": 9
        }
    },
    "20": {
        "Moves": "14",
        "ElapsedTime": {
            "Minute": 0,
            "Second": 0
        },
        "TotalElapsedTime": {
            "Hour": 0,
            "Minute": 0,
            "Second": 58
        },
        "Move": {
            "DestinationFile": 8,
            "DestinationRank": 8,
            "PieceType": "Rook",
            "Promotion": true,
            "SourceFile": 8,
            "SourceRank": 2
        }
    },
    "21": {
        "Moves": "15",
        "ElapsedTime": {
            "Minute": 0,
            "Second": 0
        },
        "TotalElapsedTime": {
            "Hour": 0,
            "Minute": 0,
            "Second": 0
        },
        "Move": {
            "DestinationFile": 9,
            "DestinationRank": 5,
            "PieceType": "Pawn",
            "SourceFile": 9,
            "SourceRank": 6
        }
    },
    "22": {
        "Moves": "16",
        "ElapsedTime": {
            "Minute": 0,
            "Second": 0
        },
        "TotalElapsedTime": {
            "Hour": 0,
            "Minute": 0,
            "Second": 58
        },
        "Move": {
            "DestinationFile": 5,
            "DestinationRank": 8,
            "PieceType": "Gold",
            "Drop": true
        }
    },
    "23": {
        "Moves": "17",
        "ElapsedTime": {
            "Minute": 0,
            "Second": 0
        },
        "TotalElapsedTime": {
            "Hour": 0,
            "Minute": 0,
            "Second": 0
        },
        "Move": {
            "Sign": "Resign"
        }
    },
    "24": {
        "Winner": "後手",
        "Moves": "16"
    }
}